tierkreis_visualization/__init__.py
tierkreis_visualization/cli.py
tierkreis_visualization/config.py
tierkreis_visualization/main.py
tierkreis_visualization/py.typed
tierkreis_visualization/data/__init__.py
tierkreis_visualization/data/eval.py
tierkreis_visualization/data/function.py
tierkreis_visualization/data/loop.py
tierkreis_visualization/data/map.py
tierkreis_visualization/data/models.py
tierkreis_visualization/data/workflows.py
tierkreis_visualization/routers/__init__.py
tierkreis_visualization/routers/models.py
tierkreis_visualization/routers/navigation.py
tierkreis_visualization/routers/workflows.py
tierkreis_visualization/static/_types.js
tierkreis_visualization/static/eventstream.js
tierkreis_visualization/static/favicon.svg
tierkreis_visualization/static/index.css
tierkreis_visualization/static/macros.breadcrumbs.html.css
tierkreis_visualization/static/network.js
tierkreis_visualization/static/normalize.css
tierkreis_visualization/static/tokens.js
tierkreis_visualization/static/utils.js
tierkreis_visualization/static/vis-network.min.js
tierkreis_visualization/static/workflows.html.css
tierkreis_visualization/static/dist/.gitignore
tierkreis_visualization/static/dist/favicon.svg
tierkreis_visualization/static/dist/index.html
tierkreis_visualization/static/dist/assets/index-BR5TeJUK.js
tierkreis_visualization/static/dist/assets/index-DrdxYMiZ.css
tierkreis_visualization/templates/eval.jinja
tierkreis_visualization/templates/fallback.jinja
tierkreis_visualization/templates/function.jinja
tierkreis_visualization/templates/index.html
tierkreis_visualization/templates/loop.jinja
tierkreis_visualization/templates/map.jinja
tierkreis_visualization/templates/unavailable.jinja
tierkreis_visualization/templates/workflows.html
tierkreis_visualization/templates/macros/breadcrumbs.html
tierkreis_visualization/templates/macros/common_head.html
tierkreis_visualization/templates/macros/header.html
tierkreis_visualization/templates/macros/json_editor.html
tierkreis_visualization-0.1.6.dist-info/METADATA
tierkreis_visualization-0.1.6.dist-info/WHEEL
tierkreis_visualization-0.1.6.dist-info/entry_points.txt
tierkreis_visualization-0.1.6.dist-info/RECORD
